barte/__init__.py
barte/__version__.py
barte/client.py
barte/exceptions.py
barte/models.py
barte_python_sdk-0.12.0.dist-info/licenses/LICENSE
barte_python_sdk-0.12.0.dist-info/METADATA
barte_python_sdk-0.12.0.dist-info/WHEEL
barte_python_sdk-0.12.0.dist-info/top_level.txt
barte_python_sdk-0.12.0.dist-info/RECORD
