Metadata-Version: 2.4
Name: barte-python-sdk
Version: 0.12.0
Summary: Python SDK for integration with Barte API
Author-email: Thiago Avelino <thiago.avelino@buser.com.br>, Erle Carrara <erle.carrara@buser.com.br>, Walison Filipe <walison.filipe@buser.com.br>, Marcos Grandesso <marcos.viana@buser.com.br>
Classifier: Programming Language :: Python :: 3
Classifier: Programming Language :: Python :: 3.11
Classifier: Programming Language :: Python :: 3.12
Requires-Python: >=3.11
License-File: LICENSE
Requires-Dist: requests<3,>=2.3
Requires-Dist: dacite==1.9.2
Requires-Dist: python-dateutil<3,>=2.8.0
Dynamic: license-file
